Metadata-Version: 1.0
Name: dist-aleksa
Version: 0.3
Summary: Gaussian and Binomial distributions
Home-page: UNKNOWN
Author: UNKNOWN
Author-email: mihajlovic.aleksa@gmail.com
License: UNKNOWN
Platform: UNKNOWN
